sphinxcontrib_prettyproof-0.0.2-py3.8-nspkg.pth
sphinxcontrib/_static/proof.css
sphinxcontrib/prettyproof/__init__.py
sphinxcontrib/prettyproof/directive.py
sphinxcontrib/prettyproof/domain.py
sphinxcontrib/prettyproof/nodes.py
sphinxcontrib/prettyproof/proof_type.py
sphinxcontrib_prettyproof-0.0.2.dist-info/LICENSE
sphinxcontrib_prettyproof-0.0.2.dist-info/METADATA
sphinxcontrib_prettyproof-0.0.2.dist-info/WHEEL
sphinxcontrib_prettyproof-0.0.2.dist-info/namespace_packages.txt
sphinxcontrib_prettyproof-0.0.2.dist-info/top_level.txt
sphinxcontrib_prettyproof-0.0.2.dist-info/RECORD
